LICENSE
MANIFEST.in
README.md
setup.py
django_header_auth.egg-info/PKG-INFO
django_header_auth.egg-info/SOURCES.txt
django_header_auth.egg-info/dependency_links.txt
django_header_auth.egg-info/top_level.txt
header_auth/__init__.py
header_auth/middleware.py
header_auth/settings.py
tests/__init__.py
tests/django_settings.py
tests/middleware_tests.py